pacifico/__init__.py
pacifico/core/Object.py
pacifico/core/__init__.py
pacifico/core/Service/Service.py
pacifico/core/Service/__init__.py
pacifico/core/Service/Field/Field.py
pacifico/core/Service/Field/FieldDataType.py
pacifico/core/Service/Field/FieldQuality.py
pacifico/core/Service/Field/FieldReport.py
pacifico/core/Service/Field/FieldTicker.py
pacifico/core/Service/Field/FieldTimeInterval.py
pacifico/core/Service/Field/FieldVersion.py
pacifico/core/Service/Field/__init__.py
pacifico/core/Service/ServiceRequest/ServiceRequest.py
pacifico/core/Service/ServiceRequest/__init__.py
pacifico/core/Service/ServiceRequest/ServiceRequestApplication/ServiceRequestApplication.py
pacifico/core/Service/ServiceRequest/ServiceRequestApplication/__init__.py
pacifico/core/Service/ServiceRequest/ServiceRequestDataPoint/ServiceRequestDataPoint.py
pacifico/core/Service/ServiceRequest/ServiceRequestDataPoint/ServiceRequestDataPointComment.py
pacifico/core/Service/ServiceRequest/ServiceRequestDataPoint/ServiceRequestDataPointReport.py
pacifico/core/Service/ServiceRequest/ServiceRequestDataPoint/ServiceRequestDataPointValue.py
pacifico/core/Service/ServiceRequest/ServiceRequestDataPoint/__init__.py
pacifico/core/main/__init__.py
pacifico/core/main/pacifico.py
pacifico/util/Arguments.py
pacifico/util/Dates.py
pacifico/util/Downloader.py
pacifico/util/Enumerations.py
pacifico/util/Format.py
pacifico/util/Installer.py
pacifico/util/Output.py
pacifico/util/Variant.py
pacifico/util/__init__.py
pacifico-0.0.9.42.dist-info/licenses/LICENSE
pacifico_devel/Message.py
pacifico_devel/__init__.py
pacifico_devel/api/__init__.py
pacifico_devel/api/pacifico.py
pacifico_devel/api/src/__init__.py
pacifico_devel/api/src/core/Object.py
pacifico_devel/api/src/core/__init__.py
pacifico_devel/api/src/core/Service/Service.py
pacifico_devel/api/src/core/Service/__init__.py
pacifico_devel/api/src/core/Service/Field/Field.py
pacifico_devel/api/src/core/Service/Field/FieldDataType.py
pacifico_devel/api/src/core/Service/Field/FieldQuality.py
pacifico-0.0.9.42.dist-info/METADATA
pacifico-0.0.9.42.dist-info/WHEEL
pacifico-0.0.9.42.dist-info/top_level.txt
pacifico-0.0.9.42.dist-info/RECORD
