Metadata-Version: 2.4
Name: pacifico
Version: 0.0.9.42
Summary: This repository holds the pacifico user Python package for the API (client source code).
Home-page: https://github.com/BurrusFinancialIntelligence/pacifico-client.git
Author: Pacifico
Author-email: pacifico@bfi.lat
Project-URL: Bug Tracker, https://github.com/BurrusFinancialIntelligence/pacifico-client.git/issues
Classifier: Programming Language :: Python :: 3
Classifier: License :: Other/Proprietary License
Classifier: Operating System :: OS Independent
Requires-Python: >=3.6
License-File: LICENSE
Requires-Dist: julian
Requires-Dist: numpy
Requires-Dist: pandas
Requires-Dist: python-dateutil
Requires-Dist: pytz
Requires-Dist: paramiko==3.5.1
Requires-Dist: requests
Requires-Dist: six
Requires-Dist: urllib3
Requires-Dist: selenium
Requires-Dist: boto3
Requires-Dist: webdriver-manager
Requires-Dist: xlrd
Requires-Dist: pysftp
Dynamic: license-file
